{
  "started_utc": "2026-02-19T20:09:58.063711Z",
  "timings_sec": {
    "discovery": 0.019,
    "fingerprinting": 2.029,
    "tls_scanning": 0.16,
    "ssh_scanning": 0.004,
    "risk_engine": 0.0,
    "db_persist": 0.004
  },
  "profile": "standard",
  "discovery_mode": "nmap",
  "cache_enabled": false,
  "safe_mode": false,
  "rate_limit": 0.0,
  "counts": {
    "targets_total": 10,
    "tls_candidates": 6,
    "ssh_candidates": 1,
    "inventory_other": 3
  },
  "ended_utc": "2026-02-19T20:10:00.288232Z",
  "protocol_counts": {
    "UNKNOWN": 1,
    "HTTP": 2,
    "TLS": 6,
    "SSH": 1
  },
  "error_categories": {}
}